pycrumbs/__init__.py
pycrumbs/py.typed
pycrumbs/track.py
pycrumbs-0.4.0.dist-info/METADATA
pycrumbs-0.4.0.dist-info/WHEEL
pycrumbs-0.4.0.dist-info/licenses/LICENSE
pycrumbs-0.4.0.dist-info/RECORD
