Metadata-Version: 2.4
Name: pycrumbs
Version: 0.4.0
Summary: Tool for automatically storing information about Python processes.
License-Expression: MIT
License-File: LICENSE
Keywords: tracking,vcs,version control
Author: Chris Bridge
Author-email: <chrisbridge44@gmail.com>
Requires-Python: >=3.10
Classifier: Topic :: Software Development :: Build Tools
Classifier: License :: OSI Approved :: MIT License
Classifier: Topic :: Software Development :: Libraries :: Python Modules
Classifier: Programming Language :: Python
Classifier: Topic :: Scientific/Engineering :: Artificial Intelligence
Classifier: Topic :: Software Development :: Quality Assurance
Classifier: Topic :: Software Development :: Version Control
Classifier: Topic :: Software Development :: Version Control :: Git
Classifier: Topic :: System :: Filesystems
Classifier: Topic :: Utilities
Requires-Dist: GitPython (>=3.0.0)
